<?xml version="1.0"?>
<odoo>
    <!-- Code to add Qualified lost button on crm form view -->
    <record id="view_crm_lead_form_inherit" model="ir.ui.view">
        <field name="name">crm.lead.form.inherit</field>
        <field name="model">crm.lead</field>
        <field name="inherit_id" ref="crm.crm_lead_view_form"/>
        <field name="arch" type="xml">
            <xpath expr="//field[@name='lost_reason_id']" position="before">
                <field name="clinic_type"/>
                <field name="requirements"/>
            </xpath>   
        </field>
    </record>
</odoo>